{
    "date": "20230329",
    "time": 400,
    "output": [
        {
            "date": "Wed 29-03-2023",
            "time": "05:00",
            "gl": 3.56,
            "uscm": 6480.48
        },
        {
            "date": "Wed 29-03-2023",
            "time": "06:00",
            "gl": 3.48,
            "uscm": 6326.66
        },
        {
            "date": "Wed 29-03-2023",
            "time": "07:00",
            "gl": 3.28,
            "uscm": 5968.33
        },
        {
            "date": "Wed 29-03-2023",
            "time": "08:00",
            "gl": 3.14,
            "uscm": 5710.32
        },
        {
            "date": "Wed 29-03-2023",
            "time": "09:00",
            "gl": 3.09,
            "uscm": 5625.6
        },
        {
            "date": "Wed 29-03-2023",
            "time": "10:00",
            "gl": 3.02,
            "uscm": 5499.25
        },
        {
            "date": "Wed 29-03-2023",
            "time": "11:00",
            "gl": 3.16,
            "uscm": 5750.95
        },
        {
            "date": "Wed 29-03-2023",
            "time": "12:00",
            "gl": 3.46,
            "uscm": 6282.61
        },
        {
            "date": "Wed 29-03-2023",
            "time": "13:00",
            "gl": 3.62,
            "uscm": 6587.88
        },
        {
            "date": "Wed 29-03-2023",
            "time": "14:00",
            "gl": 3.8,
            "uscm": 6913.75
        },
        {
            "date": "Wed 29-03-2023",
            "time": "15:00",
            "gl": 3.7,
            "uscm": 6722.26
        },
        {
            "date": "Wed 29-03-2023",
            "time": "16:00",
            "gl": 3.47,
            "uscm": 6310.05
        },
        {
            "date": "Wed 29-03-2023",
            "time": "17:00",
            "gl": 3.25,
            "uscm": 5913.91
        },
        {
            "date": "Wed 29-03-2023",
            "time": "18:00",
            "gl": 2.99,
            "uscm": 5444.91
        },
        {
            "date": "Wed 29-03-2023",
            "time": "19:00",
            "gl": 2.73,
            "uscm": 4961.95
        },
        {
            "date": "Wed 29-03-2023",
            "time": "20:00",
            "gl": 2.61,
            "uscm": 4754.37
        },
        {
            "date": "Wed 29-03-2023",
            "time": "21:00",
            "gl": 2.6,
            "uscm": 4723.71
        },
        {
            "date": "Wed 29-03-2023",
            "time": "22:00",
            "gl": 2.56,
            "uscm": 4654.49
        },
        {
            "date": "Wed 29-03-2023",
            "time": "23:00",
            "gl": 2.66,
            "uscm": 4828.17
        },
        {
            "date": "Thu 30-03-2023",
            "time": "00:00",
            "gl": 2.86,
            "uscm": 5202.05
        },
        {
            "date": "Thu 30-03-2023",
            "time": "01:00",
            "gl": 3.13,
            "uscm": 5686.35
        },
        {
            "date": "Thu 30-03-2023",
            "time": "02:00",
            "gl": 3.36,
            "uscm": 6101.86
        },
        {
            "date": "Thu 30-03-2023",
            "time": "03:00",
            "gl": 3.65,
            "uscm": 6636.49
        },
        {
            "date": "Thu 30-03-2023",
            "time": "04:00",
            "gl": 3.86,
            "uscm": 7011.17
        }
    ]
}