{
    "date": "20230328",
    "time": 2200,
    "output": [
        {
            "date": "Tue 28-03-2023",
            "time": "23:00",
            "gl": 1.04,
            "uscm": 1894.38
        },
        {
            "date": "Wed 29-03-2023",
            "time": "00:00",
            "gl": 1.21,
            "uscm": 2208.9
        },
        {
            "date": "Wed 29-03-2023",
            "time": "01:00",
            "gl": 1.64,
            "uscm": 2982.83
        },
        {
            "date": "Wed 29-03-2023",
            "time": "02:00",
            "gl": 2.06,
            "uscm": 3737.35
        },
        {
            "date": "Wed 29-03-2023",
            "time": "03:00",
            "gl": 2.66,
            "uscm": 4830.44
        },
        {
            "date": "Wed 29-03-2023",
            "time": "04:00",
            "gl": 3.13,
            "uscm": 5687.21
        },
        {
            "date": "Wed 29-03-2023",
            "time": "05:00",
            "gl": 3.3,
            "uscm": 6000.45
        },
        {
            "date": "Wed 29-03-2023",
            "time": "06:00",
            "gl": 3.33,
            "uscm": 6059.85
        },
        {
            "date": "Wed 29-03-2023",
            "time": "07:00",
            "gl": 3.16,
            "uscm": 5747.09
        },
        {
            "date": "Wed 29-03-2023",
            "time": "08:00",
            "gl": 3.07,
            "uscm": 5588.31
        },
        {
            "date": "Wed 29-03-2023",
            "time": "09:00",
            "gl": 2.98,
            "uscm": 5413.33
        },
        {
            "date": "Wed 29-03-2023",
            "time": "10:00",
            "gl": 3.11,
            "uscm": 5662.38
        },
        {
            "date": "Wed 29-03-2023",
            "time": "11:00",
            "gl": 3.21,
            "uscm": 5830.82
        },
        {
            "date": "Wed 29-03-2023",
            "time": "12:00",
            "gl": 3.33,
            "uscm": 6052.98
        },
        {
            "date": "Wed 29-03-2023",
            "time": "13:00",
            "gl": 3.41,
            "uscm": 6207.06
        },
        {
            "date": "Wed 29-03-2023",
            "time": "14:00",
            "gl": 3.64,
            "uscm": 6613.6
        },
        {
            "date": "Wed 29-03-2023",
            "time": "15:00",
            "gl": 3.65,
            "uscm": 6629.7
        },
        {
            "date": "Wed 29-03-2023",
            "time": "16:00",
            "gl": 3.65,
            "uscm": 6644.93
        },
        {
            "date": "Wed 29-03-2023",
            "time": "17:00",
            "gl": 3.27,
            "uscm": 5947.46
        },
        {
            "date": "Wed 29-03-2023",
            "time": "18:00",
            "gl": 2.76,
            "uscm": 5023.08
        },
        {
            "date": "Wed 29-03-2023",
            "time": "19:00",
            "gl": 2.39,
            "uscm": 4351.07
        },
        {
            "date": "Wed 29-03-2023",
            "time": "20:00",
            "gl": 2.06,
            "uscm": 3742.54
        },
        {
            "date": "Wed 29-03-2023",
            "time": "21:00",
            "gl": 1.93,
            "uscm": 3503.89
        },
        {
            "date": "Wed 29-03-2023",
            "time": "22:00",
            "gl": 1.76,
            "uscm": 3206.7
        }
    ]
}