{
    "date": "20230304",
    "time": 600,
    "output": [
        {
            "date": "Sat 04-03-2023",
            "time": "07:00",
            "gl": 1.76,
            "uscm": 3191.26
        },
        {
            "date": "Sat 04-03-2023",
            "time": "08:00",
            "gl": 1.87,
            "uscm": 3395.8
        },
        {
            "date": "Sat 04-03-2023",
            "time": "09:00",
            "gl": 2.25,
            "uscm": 4098.49
        },
        {
            "date": "Sat 04-03-2023",
            "time": "10:00",
            "gl": 2.84,
            "uscm": 5166.93
        },
        {
            "date": "Sat 04-03-2023",
            "time": "11:00",
            "gl": 3.17,
            "uscm": 5763.02
        },
        {
            "date": "Sat 04-03-2023",
            "time": "12:00",
            "gl": 3.44,
            "uscm": 6251.15
        },
        {
            "date": "Sat 04-03-2023",
            "time": "13:00",
            "gl": 3.35,
            "uscm": 6082.87
        },
        {
            "date": "Sat 04-03-2023",
            "time": "14:00",
            "gl": 3.17,
            "uscm": 5763.85
        },
        {
            "date": "Sat 04-03-2023",
            "time": "15:00",
            "gl": 3.01,
            "uscm": 5477.23
        },
        {
            "date": "Sat 04-03-2023",
            "time": "16:00",
            "gl": 2.9,
            "uscm": 5278.48
        },
        {
            "date": "Sat 04-03-2023",
            "time": "17:00",
            "gl": 3.0,
            "uscm": 5452.89
        },
        {
            "date": "Sat 04-03-2023",
            "time": "18:00",
            "gl": 3.19,
            "uscm": 5800.37
        },
        {
            "date": "Sat 04-03-2023",
            "time": "19:00",
            "gl": 3.32,
            "uscm": 6040.53
        },
        {
            "date": "Sat 04-03-2023",
            "time": "20:00",
            "gl": 3.25,
            "uscm": 5903.21
        },
        {
            "date": "Sat 04-03-2023",
            "time": "21:00",
            "gl": 3.2,
            "uscm": 5823.25
        },
        {
            "date": "Sat 04-03-2023",
            "time": "22:00",
            "gl": 3.09,
            "uscm": 5612.65
        },
        {
            "date": "Sat 04-03-2023",
            "time": "23:00",
            "gl": 3.06,
            "uscm": 5570.27
        },
        {
            "date": "Sun 05-03-2023",
            "time": "00:00",
            "gl": 2.87,
            "uscm": 5215.95
        },
        {
            "date": "Sun 05-03-2023",
            "time": "01:00",
            "gl": 2.57,
            "uscm": 4674.33
        },
        {
            "date": "Sun 05-03-2023",
            "time": "02:00",
            "gl": 2.24,
            "uscm": 4070.73
        },
        {
            "date": "Sun 05-03-2023",
            "time": "03:00",
            "gl": 1.96,
            "uscm": 3570.99
        },
        {
            "date": "Sun 05-03-2023",
            "time": "04:00",
            "gl": 1.72,
            "uscm": 3123.34
        },
        {
            "date": "Sun 05-03-2023",
            "time": "05:00",
            "gl": 1.55,
            "uscm": 2812.37
        },
        {
            "date": "Sun 05-03-2023",
            "time": "06:00",
            "gl": 1.76,
            "uscm": 3199.94
        }
    ]
}