{
    "date": "20230211",
    "time": 1600,
    "output": [
        {
            "date": "Sat 11-02-2023",
            "time": "17:00",
            "gl": 5.53,
            "uscm": 10049.05
        },
        {
            "date": "Sat 11-02-2023",
            "time": "18:00",
            "gl": 5.04,
            "uscm": 9166.64
        },
        {
            "date": "Sat 11-02-2023",
            "time": "19:00",
            "gl": 4.7,
            "uscm": 8536.58
        },
        {
            "date": "Sat 11-02-2023",
            "time": "20:00",
            "gl": 4.56,
            "uscm": 8283.38
        },
        {
            "date": "Sat 11-02-2023",
            "time": "21:00",
            "gl": 4.81,
            "uscm": 8750.56
        },
        {
            "date": "Sat 11-02-2023",
            "time": "22:00",
            "gl": 5.09,
            "uscm": 9258.13
        },
        {
            "date": "Sat 11-02-2023",
            "time": "23:00",
            "gl": 5.55,
            "uscm": 10091.67
        },
        {
            "date": "Sun 12-02-2023",
            "time": "00:00",
            "gl": 5.95,
            "uscm": 10816.87
        },
        {
            "date": "Sun 12-02-2023",
            "time": "01:00",
            "gl": 5.88,
            "uscm": 10682.84
        },
        {
            "date": "Sun 12-02-2023",
            "time": "02:00",
            "gl": 5.57,
            "uscm": 10134.19
        },
        {
            "date": "Sun 12-02-2023",
            "time": "03:00",
            "gl": 5.06,
            "uscm": 9191.78
        },
        {
            "date": "Sun 12-02-2023",
            "time": "04:00",
            "gl": 4.42,
            "uscm": 8030.83
        },
        {
            "date": "Sun 12-02-2023",
            "time": "05:00",
            "gl": 4.15,
            "uscm": 7537.78
        },
        {
            "date": "Sun 12-02-2023",
            "time": "06:00",
            "gl": 4.0,
            "uscm": 7266.59
        },
        {
            "date": "Sun 12-02-2023",
            "time": "07:00",
            "gl": 3.82,
            "uscm": 6947.01
        },
        {
            "date": "Sun 12-02-2023",
            "time": "08:00",
            "gl": 4.06,
            "uscm": 7378.16
        },
        {
            "date": "Sun 12-02-2023",
            "time": "09:00",
            "gl": 4.45,
            "uscm": 8086.08
        },
        {
            "date": "Sun 12-02-2023",
            "time": "10:00",
            "gl": 5.11,
            "uscm": 9298.6
        },
        {
            "date": "Sun 12-02-2023",
            "time": "11:00",
            "gl": 5.75,
            "uscm": 10455.56
        },
        {
            "date": "Sun 12-02-2023",
            "time": "12:00",
            "gl": 6.31,
            "uscm": 11475.6
        },
        {
            "date": "Sun 12-02-2023",
            "time": "13:00",
            "gl": 6.49,
            "uscm": 11804.28
        },
        {
            "date": "Sun 12-02-2023",
            "time": "14:00",
            "gl": 6.26,
            "uscm": 11384.03
        },
        {
            "date": "Sun 12-02-2023",
            "time": "15:00",
            "gl": 5.75,
            "uscm": 10448.18
        },
        {
            "date": "Sun 12-02-2023",
            "time": "16:00",
            "gl": 5.21,
            "uscm": 9472.96
        }
    ]
}