{
    "date": "20230216",
    "time": 2200,
    "output": [
        {
            "date": "Thu 16-02-2023",
            "time": "23:00",
            "gl": 4.31,
            "uscm": 7830.2
        },
        {
            "date": "Fri 17-02-2023",
            "time": "00:00",
            "gl": 4.15,
            "uscm": 7539.94
        },
        {
            "date": "Fri 17-02-2023",
            "time": "01:00",
            "gl": 4.08,
            "uscm": 7420.31
        },
        {
            "date": "Fri 17-02-2023",
            "time": "02:00",
            "gl": 4.17,
            "uscm": 7573.26
        },
        {
            "date": "Fri 17-02-2023",
            "time": "03:00",
            "gl": 4.5,
            "uscm": 8185.33
        },
        {
            "date": "Fri 17-02-2023",
            "time": "04:00",
            "gl": 4.93,
            "uscm": 8961.14
        },
        {
            "date": "Fri 17-02-2023",
            "time": "05:00",
            "gl": 5.42,
            "uscm": 9848.44
        },
        {
            "date": "Fri 17-02-2023",
            "time": "06:00",
            "gl": 5.94,
            "uscm": 10794.18
        },
        {
            "date": "Fri 17-02-2023",
            "time": "07:00",
            "gl": 6.4,
            "uscm": 11632.72
        },
        {
            "date": "Fri 17-02-2023",
            "time": "08:00",
            "gl": 6.8,
            "uscm": 12370.25
        },
        {
            "date": "Fri 17-02-2023",
            "time": "09:00",
            "gl": 7.14,
            "uscm": 12984.75
        },
        {
            "date": "Fri 17-02-2023",
            "time": "10:00",
            "gl": 7.34,
            "uscm": 13352.62
        },
        {
            "date": "Fri 17-02-2023",
            "time": "11:00",
            "gl": 7.54,
            "uscm": 13708.77
        },
        {
            "date": "Fri 17-02-2023",
            "time": "12:00",
            "gl": 7.62,
            "uscm": 13849.07
        },
        {
            "date": "Fri 17-02-2023",
            "time": "13:00",
            "gl": 7.62,
            "uscm": 13860.42
        },
        {
            "date": "Fri 17-02-2023",
            "time": "14:00",
            "gl": 7.61,
            "uscm": 13841.81
        },
        {
            "date": "Fri 17-02-2023",
            "time": "15:00",
            "gl": 7.4,
            "uscm": 13451.99
        },
        {
            "date": "Fri 17-02-2023",
            "time": "16:00",
            "gl": 7.07,
            "uscm": 12852.95
        },
        {
            "date": "Fri 17-02-2023",
            "time": "17:00",
            "gl": 6.55,
            "uscm": 11911.6
        },
        {
            "date": "Fri 17-02-2023",
            "time": "18:00",
            "gl": 6.05,
            "uscm": 11006.67
        },
        {
            "date": "Fri 17-02-2023",
            "time": "19:00",
            "gl": 5.64,
            "uscm": 10262.08
        },
        {
            "date": "Fri 17-02-2023",
            "time": "20:00",
            "gl": 5.34,
            "uscm": 9712.72
        },
        {
            "date": "Fri 17-02-2023",
            "time": "21:00",
            "gl": 4.82,
            "uscm": 8767.35
        },
        {
            "date": "Fri 17-02-2023",
            "time": "22:00",
            "gl": 4.56,
            "uscm": 8299.97
        }
    ]
}