{
    "date": "20230212",
    "time": 1800,
    "output": [
        {
            "date": "Sun 12-02-2023",
            "time": "19:00",
            "gl": 4.81,
            "uscm": 8742.97
        },
        {
            "date": "Sun 12-02-2023",
            "time": "20:00",
            "gl": 4.64,
            "uscm": 8443.53
        },
        {
            "date": "Sun 12-02-2023",
            "time": "21:00",
            "gl": 4.59,
            "uscm": 8340.12
        },
        {
            "date": "Sun 12-02-2023",
            "time": "22:00",
            "gl": 4.72,
            "uscm": 8586.4
        },
        {
            "date": "Sun 12-02-2023",
            "time": "23:00",
            "gl": 5.11,
            "uscm": 9282.34
        },
        {
            "date": "Mon 13-02-2023",
            "time": "00:00",
            "gl": 5.47,
            "uscm": 9945.7
        },
        {
            "date": "Mon 13-02-2023",
            "time": "01:00",
            "gl": 5.73,
            "uscm": 10421.46
        },
        {
            "date": "Mon 13-02-2023",
            "time": "02:00",
            "gl": 5.81,
            "uscm": 10557.85
        },
        {
            "date": "Mon 13-02-2023",
            "time": "03:00",
            "gl": 5.46,
            "uscm": 9927.42
        },
        {
            "date": "Mon 13-02-2023",
            "time": "04:00",
            "gl": 5.01,
            "uscm": 9102.15
        },
        {
            "date": "Mon 13-02-2023",
            "time": "05:00",
            "gl": 4.56,
            "uscm": 8287.69
        },
        {
            "date": "Mon 13-02-2023",
            "time": "06:00",
            "gl": 4.12,
            "uscm": 7492.86
        },
        {
            "date": "Mon 13-02-2023",
            "time": "07:00",
            "gl": 4.12,
            "uscm": 7486.95
        },
        {
            "date": "Mon 13-02-2023",
            "time": "08:00",
            "gl": 4.28,
            "uscm": 7772.94
        },
        {
            "date": "Mon 13-02-2023",
            "time": "09:00",
            "gl": 4.52,
            "uscm": 8211.28
        },
        {
            "date": "Mon 13-02-2023",
            "time": "10:00",
            "gl": 5.2,
            "uscm": 9461.92
        },
        {
            "date": "Mon 13-02-2023",
            "time": "11:00",
            "gl": 5.85,
            "uscm": 10628.79
        },
        {
            "date": "Mon 13-02-2023",
            "time": "12:00",
            "gl": 6.37,
            "uscm": 11578.73
        },
        {
            "date": "Mon 13-02-2023",
            "time": "13:00",
            "gl": 6.5,
            "uscm": 11809.15
        },
        {
            "date": "Mon 13-02-2023",
            "time": "14:00",
            "gl": 6.34,
            "uscm": 11519.93
        },
        {
            "date": "Mon 13-02-2023",
            "time": "15:00",
            "gl": 6.01,
            "uscm": 10922.32
        },
        {
            "date": "Mon 13-02-2023",
            "time": "16:00",
            "gl": 5.5,
            "uscm": 10001.36
        },
        {
            "date": "Mon 13-02-2023",
            "time": "17:00",
            "gl": 4.99,
            "uscm": 9072.96
        },
        {
            "date": "Mon 13-02-2023",
            "time": "18:00",
            "gl": 4.65,
            "uscm": 8461.35
        }
    ]
}