{
    "date": "20230325",
    "time": 1500,
    "output": [
        {
            "date": "Sat 25-03-2023",
            "time": "16:00",
            "gl": 4.41,
            "uscm": 8019.23
        },
        {
            "date": "Sat 25-03-2023",
            "time": "17:00",
            "gl": 4.2,
            "uscm": 7637.49
        },
        {
            "date": "Sat 25-03-2023",
            "time": "18:00",
            "gl": 3.98,
            "uscm": 7227.44
        },
        {
            "date": "Sat 25-03-2023",
            "time": "19:00",
            "gl": 3.82,
            "uscm": 6950.9
        },
        {
            "date": "Sat 25-03-2023",
            "time": "20:00",
            "gl": 3.99,
            "uscm": 7259.25
        },
        {
            "date": "Sat 25-03-2023",
            "time": "21:00",
            "gl": 4.14,
            "uscm": 7518.92
        },
        {
            "date": "Sat 25-03-2023",
            "time": "22:00",
            "gl": 4.5,
            "uscm": 8178.66
        },
        {
            "date": "Sat 25-03-2023",
            "time": "23:00",
            "gl": 4.86,
            "uscm": 8834.02
        },
        {
            "date": "Sun 26-03-2023",
            "time": "00:00",
            "gl": 5.09,
            "uscm": 9256.04
        },
        {
            "date": "Sun 26-03-2023",
            "time": "01:00",
            "gl": 5.28,
            "uscm": 9605.89
        },
        {
            "date": "Sun 26-03-2023",
            "time": "02:00",
            "gl": 5.21,
            "uscm": 9468.09
        },
        {
            "date": "Sun 26-03-2023",
            "time": "03:00",
            "gl": 4.83,
            "uscm": 8780.94
        },
        {
            "date": "Sun 26-03-2023",
            "time": "04:00",
            "gl": 4.57,
            "uscm": 8306.91
        },
        {
            "date": "Sun 26-03-2023",
            "time": "05:00",
            "gl": 4.28,
            "uscm": 7773.56
        },
        {
            "date": "Sun 26-03-2023",
            "time": "06:00",
            "gl": 3.99,
            "uscm": 7258.26
        },
        {
            "date": "Sun 26-03-2023",
            "time": "07:00",
            "gl": 4.1,
            "uscm": 7454.53
        },
        {
            "date": "Sun 26-03-2023",
            "time": "08:00",
            "gl": 4.26,
            "uscm": 7737.09
        },
        {
            "date": "Sun 26-03-2023",
            "time": "09:00",
            "gl": 4.62,
            "uscm": 8395.84
        },
        {
            "date": "Sun 26-03-2023",
            "time": "10:00",
            "gl": 4.91,
            "uscm": 8920.91
        },
        {
            "date": "Sun 26-03-2023",
            "time": "11:00",
            "gl": 5.16,
            "uscm": 9379.66
        },
        {
            "date": "Sun 26-03-2023",
            "time": "12:00",
            "gl": 5.31,
            "uscm": 9661.05
        },
        {
            "date": "Sun 26-03-2023",
            "time": "13:00",
            "gl": 5.14,
            "uscm": 9345.27
        },
        {
            "date": "Sun 26-03-2023",
            "time": "14:00",
            "gl": 4.84,
            "uscm": 8800.1
        },
        {
            "date": "Sun 26-03-2023",
            "time": "15:00",
            "gl": 4.49,
            "uscm": 8165.93
        }
    ]
}