{
    "date": "20230316",
    "time": 1500,
    "output": [
        {
            "date": "Thu 16-03-2023",
            "time": "16:00",
            "gl": 4.43,
            "uscm": 8047.98
        },
        {
            "date": "Thu 16-03-2023",
            "time": "17:00",
            "gl": 4.08,
            "uscm": 7410.94
        },
        {
            "date": "Thu 16-03-2023",
            "time": "18:00",
            "gl": 3.71,
            "uscm": 6746.3
        },
        {
            "date": "Thu 16-03-2023",
            "time": "19:00",
            "gl": 3.41,
            "uscm": 6200.1
        },
        {
            "date": "Thu 16-03-2023",
            "time": "20:00",
            "gl": 3.21,
            "uscm": 5835.12
        },
        {
            "date": "Thu 16-03-2023",
            "time": "21:00",
            "gl": 3.02,
            "uscm": 5486.85
        },
        {
            "date": "Thu 16-03-2023",
            "time": "22:00",
            "gl": 2.93,
            "uscm": 5328.25
        },
        {
            "date": "Thu 16-03-2023",
            "time": "23:00",
            "gl": 2.96,
            "uscm": 5379.6
        },
        {
            "date": "Fri 17-03-2023",
            "time": "00:00",
            "gl": 3.12,
            "uscm": 5678.39
        },
        {
            "date": "Fri 17-03-2023",
            "time": "01:00",
            "gl": 3.35,
            "uscm": 6094.45
        },
        {
            "date": "Fri 17-03-2023",
            "time": "02:00",
            "gl": 3.67,
            "uscm": 6680.16
        },
        {
            "date": "Fri 17-03-2023",
            "time": "03:00",
            "gl": 3.94,
            "uscm": 7154.99
        },
        {
            "date": "Fri 17-03-2023",
            "time": "04:00",
            "gl": 4.26,
            "uscm": 7744.13
        },
        {
            "date": "Fri 17-03-2023",
            "time": "05:00",
            "gl": 4.5,
            "uscm": 8181.55
        },
        {
            "date": "Fri 17-03-2023",
            "time": "06:00",
            "gl": 4.7,
            "uscm": 8546.97
        },
        {
            "date": "Fri 17-03-2023",
            "time": "07:00",
            "gl": 5.05,
            "uscm": 9177.19
        },
        {
            "date": "Fri 17-03-2023",
            "time": "08:00",
            "gl": 5.25,
            "uscm": 9542.77
        },
        {
            "date": "Fri 17-03-2023",
            "time": "09:00",
            "gl": 5.44,
            "uscm": 9884.04
        },
        {
            "date": "Fri 17-03-2023",
            "time": "10:00",
            "gl": 5.51,
            "uscm": 10011.95
        },
        {
            "date": "Fri 17-03-2023",
            "time": "11:00",
            "gl": 5.54,
            "uscm": 10074.95
        },
        {
            "date": "Fri 17-03-2023",
            "time": "12:00",
            "gl": 5.5,
            "uscm": 9995.23
        },
        {
            "date": "Fri 17-03-2023",
            "time": "13:00",
            "gl": 5.22,
            "uscm": 9492.94
        },
        {
            "date": "Fri 17-03-2023",
            "time": "14:00",
            "gl": 4.87,
            "uscm": 8849.43
        },
        {
            "date": "Fri 17-03-2023",
            "time": "15:00",
            "gl": 4.56,
            "uscm": 8291.61
        }
    ]
}