{
    "date": "20230117",
    "time": 800,
    "output": [
        {
            "date": "Tue 17-01-2023",
            "time": "09:00",
            "gl": 0.43,
            "uscm": 775.97
        },
        {
            "date": "Tue 17-01-2023",
            "time": "10:00",
            "gl": 0.49,
            "uscm": 893.73
        },
        {
            "date": "Tue 17-01-2023",
            "time": "11:00",
            "gl": 0.55,
            "uscm": 1005.43
        },
        {
            "date": "Tue 17-01-2023",
            "time": "12:00",
            "gl": 0.62,
            "uscm": 1121.21
        },
        {
            "date": "Tue 17-01-2023",
            "time": "13:00",
            "gl": 0.74,
            "uscm": 1338.25
        },
        {
            "date": "Tue 17-01-2023",
            "time": "14:00",
            "gl": 0.77,
            "uscm": 1396.41
        },
        {
            "date": "Tue 17-01-2023",
            "time": "15:00",
            "gl": 0.81,
            "uscm": 1476.2
        },
        {
            "date": "Tue 17-01-2023",
            "time": "16:00",
            "gl": 0.79,
            "uscm": 1441.1
        },
        {
            "date": "Tue 17-01-2023",
            "time": "17:00",
            "gl": 0.71,
            "uscm": 1296.15
        },
        {
            "date": "Tue 17-01-2023",
            "time": "18:00",
            "gl": 0.67,
            "uscm": 1219.16
        },
        {
            "date": "Tue 17-01-2023",
            "time": "19:00",
            "gl": 0.57,
            "uscm": 1042.78
        },
        {
            "date": "Tue 17-01-2023",
            "time": "20:00",
            "gl": 0.48,
            "uscm": 871.46
        },
        {
            "date": "Tue 17-01-2023",
            "time": "21:00",
            "gl": 0.43,
            "uscm": 781.11
        },
        {
            "date": "Tue 17-01-2023",
            "time": "22:00",
            "gl": 0.42,
            "uscm": 761.89
        },
        {
            "date": "Tue 17-01-2023",
            "time": "23:00",
            "gl": 0.39,
            "uscm": 715.35
        },
        {
            "date": "Wed 18-01-2023",
            "time": "00:00",
            "gl": 0.39,
            "uscm": 705.38
        },
        {
            "date": "Wed 18-01-2023",
            "time": "01:00",
            "gl": 0.34,
            "uscm": 622.79
        },
        {
            "date": "Wed 18-01-2023",
            "time": "02:00",
            "gl": 0.38,
            "uscm": 689.91
        },
        {
            "date": "Wed 18-01-2023",
            "time": "03:00",
            "gl": 0.42,
            "uscm": 756.1
        },
        {
            "date": "Wed 18-01-2023",
            "time": "04:00",
            "gl": 0.45,
            "uscm": 812.73
        },
        {
            "date": "Wed 18-01-2023",
            "time": "05:00",
            "gl": 0.48,
            "uscm": 870.2
        },
        {
            "date": "Wed 18-01-2023",
            "time": "06:00",
            "gl": 0.51,
            "uscm": 935.13
        },
        {
            "date": "Wed 18-01-2023",
            "time": "07:00",
            "gl": 0.54,
            "uscm": 987.03
        },
        {
            "date": "Wed 18-01-2023",
            "time": "08:00",
            "gl": 0.51,
            "uscm": 928.64
        }
    ]
}