{
    "date": "20230211",
    "time": 100,
    "output": [
        {
            "date": "Sat 11-02-2023",
            "time": "02:00",
            "gl": 5.84,
            "uscm": 10615.97
        },
        {
            "date": "Sat 11-02-2023",
            "time": "03:00",
            "gl": 5.3,
            "uscm": 9641.22
        },
        {
            "date": "Sat 11-02-2023",
            "time": "04:00",
            "gl": 4.71,
            "uscm": 8569.86
        },
        {
            "date": "Sat 11-02-2023",
            "time": "05:00",
            "gl": 4.38,
            "uscm": 7960.06
        },
        {
            "date": "Sat 11-02-2023",
            "time": "06:00",
            "gl": 4.3,
            "uscm": 7820.85
        },
        {
            "date": "Sat 11-02-2023",
            "time": "07:00",
            "gl": 4.19,
            "uscm": 7621.52
        },
        {
            "date": "Sat 11-02-2023",
            "time": "08:00",
            "gl": 4.27,
            "uscm": 7770.56
        },
        {
            "date": "Sat 11-02-2023",
            "time": "09:00",
            "gl": 4.5,
            "uscm": 8174.62
        },
        {
            "date": "Sat 11-02-2023",
            "time": "10:00",
            "gl": 4.85,
            "uscm": 8825.55
        },
        {
            "date": "Sat 11-02-2023",
            "time": "11:00",
            "gl": 5.56,
            "uscm": 10105.71
        },
        {
            "date": "Sat 11-02-2023",
            "time": "12:00",
            "gl": 6.18,
            "uscm": 11238.92
        },
        {
            "date": "Sat 11-02-2023",
            "time": "13:00",
            "gl": 6.45,
            "uscm": 11725.57
        },
        {
            "date": "Sat 11-02-2023",
            "time": "14:00",
            "gl": 6.64,
            "uscm": 12070.66
        },
        {
            "date": "Sat 11-02-2023",
            "time": "15:00",
            "gl": 6.34,
            "uscm": 11519.11
        },
        {
            "date": "Sat 11-02-2023",
            "time": "16:00",
            "gl": 5.74,
            "uscm": 10441.16
        },
        {
            "date": "Sat 11-02-2023",
            "time": "17:00",
            "gl": 5.2,
            "uscm": 9459.5
        },
        {
            "date": "Sat 11-02-2023",
            "time": "18:00",
            "gl": 4.77,
            "uscm": 8669.76
        },
        {
            "date": "Sat 11-02-2023",
            "time": "19:00",
            "gl": 4.48,
            "uscm": 8137.01
        },
        {
            "date": "Sat 11-02-2023",
            "time": "20:00",
            "gl": 4.52,
            "uscm": 8218.75
        },
        {
            "date": "Sat 11-02-2023",
            "time": "21:00",
            "gl": 4.87,
            "uscm": 8855.54
        },
        {
            "date": "Sat 11-02-2023",
            "time": "22:00",
            "gl": 5.46,
            "uscm": 9931.54
        },
        {
            "date": "Sat 11-02-2023",
            "time": "23:00",
            "gl": 5.89,
            "uscm": 10717.7
        },
        {
            "date": "Sun 12-02-2023",
            "time": "00:00",
            "gl": 6.22,
            "uscm": 11311.69
        },
        {
            "date": "Sun 12-02-2023",
            "time": "01:00",
            "gl": 6.23,
            "uscm": 11320.49
        }
    ]
}