{
    "date": "20230322",
    "time": 800,
    "output": [
        {
            "date": "Wed 22-03-2023",
            "time": "09:00",
            "gl": 4.74,
            "uscm": 8624.0
        },
        {
            "date": "Wed 22-03-2023",
            "time": "10:00",
            "gl": 5.07,
            "uscm": 9213.25
        },
        {
            "date": "Wed 22-03-2023",
            "time": "11:00",
            "gl": 5.06,
            "uscm": 9207.17
        },
        {
            "date": "Wed 22-03-2023",
            "time": "12:00",
            "gl": 5.04,
            "uscm": 9171.81
        },
        {
            "date": "Wed 22-03-2023",
            "time": "13:00",
            "gl": 4.98,
            "uscm": 9061.25
        },
        {
            "date": "Wed 22-03-2023",
            "time": "14:00",
            "gl": 4.75,
            "uscm": 8629.39
        },
        {
            "date": "Wed 22-03-2023",
            "time": "15:00",
            "gl": 4.6,
            "uscm": 8372.2
        },
        {
            "date": "Wed 22-03-2023",
            "time": "16:00",
            "gl": 4.54,
            "uscm": 8257.05
        },
        {
            "date": "Wed 22-03-2023",
            "time": "17:00",
            "gl": 4.42,
            "uscm": 8027.99
        },
        {
            "date": "Wed 22-03-2023",
            "time": "18:00",
            "gl": 4.67,
            "uscm": 8483.26
        },
        {
            "date": "Wed 22-03-2023",
            "time": "19:00",
            "gl": 4.82,
            "uscm": 8767.21
        },
        {
            "date": "Wed 22-03-2023",
            "time": "20:00",
            "gl": 5.07,
            "uscm": 9218.54
        },
        {
            "date": "Wed 22-03-2023",
            "time": "21:00",
            "gl": 5.28,
            "uscm": 9594.96
        },
        {
            "date": "Wed 22-03-2023",
            "time": "22:00",
            "gl": 5.19,
            "uscm": 9439.87
        },
        {
            "date": "Wed 22-03-2023",
            "time": "23:00",
            "gl": 5.07,
            "uscm": 9223.76
        },
        {
            "date": "Thu 23-03-2023",
            "time": "00:00",
            "gl": 4.93,
            "uscm": 8960.31
        },
        {
            "date": "Thu 23-03-2023",
            "time": "01:00",
            "gl": 4.57,
            "uscm": 8301.05
        },
        {
            "date": "Thu 23-03-2023",
            "time": "02:00",
            "gl": 4.19,
            "uscm": 7624.97
        },
        {
            "date": "Thu 23-03-2023",
            "time": "03:00",
            "gl": 3.83,
            "uscm": 6965.59
        },
        {
            "date": "Thu 23-03-2023",
            "time": "04:00",
            "gl": 3.71,
            "uscm": 6748.93
        },
        {
            "date": "Thu 23-03-2023",
            "time": "05:00",
            "gl": 3.79,
            "uscm": 6883.06
        },
        {
            "date": "Thu 23-03-2023",
            "time": "06:00",
            "gl": 3.84,
            "uscm": 6979.83
        },
        {
            "date": "Thu 23-03-2023",
            "time": "07:00",
            "gl": 3.94,
            "uscm": 7172.07
        },
        {
            "date": "Thu 23-03-2023",
            "time": "08:00",
            "gl": 4.17,
            "uscm": 7585.78
        }
    ]
}