{
    "date": "20230105",
    "time": 500,
    "output": [
        {
            "date": "Thu 05-01-2023",
            "time": "06:00",
            "gl": 0.21,
            "uscm": 388.87
        },
        {
            "date": "Thu 05-01-2023",
            "time": "07:00",
            "gl": 0.22,
            "uscm": 408.46
        },
        {
            "date": "Thu 05-01-2023",
            "time": "08:00",
            "gl": 0.24,
            "uscm": 443.09
        },
        {
            "date": "Thu 05-01-2023",
            "time": "09:00",
            "gl": 0.25,
            "uscm": 460.56
        },
        {
            "date": "Thu 05-01-2023",
            "time": "10:00",
            "gl": 0.29,
            "uscm": 525.6
        },
        {
            "date": "Thu 05-01-2023",
            "time": "11:00",
            "gl": 0.31,
            "uscm": 554.81
        },
        {
            "date": "Thu 05-01-2023",
            "time": "12:00",
            "gl": 0.32,
            "uscm": 584.74
        },
        {
            "date": "Thu 05-01-2023",
            "time": "13:00",
            "gl": 0.33,
            "uscm": 593.51
        },
        {
            "date": "Thu 05-01-2023",
            "time": "14:00",
            "gl": 0.32,
            "uscm": 588.39
        },
        {
            "date": "Thu 05-01-2023",
            "time": "15:00",
            "gl": 0.32,
            "uscm": 585.06
        },
        {
            "date": "Thu 05-01-2023",
            "time": "16:00",
            "gl": 0.31,
            "uscm": 566.56
        },
        {
            "date": "Thu 05-01-2023",
            "time": "17:00",
            "gl": 0.31,
            "uscm": 568.78
        },
        {
            "date": "Thu 05-01-2023",
            "time": "18:00",
            "gl": 0.32,
            "uscm": 584.8
        },
        {
            "date": "Thu 05-01-2023",
            "time": "19:00",
            "gl": 0.33,
            "uscm": 592.5
        },
        {
            "date": "Thu 05-01-2023",
            "time": "20:00",
            "gl": 0.32,
            "uscm": 587.08
        },
        {
            "date": "Thu 05-01-2023",
            "time": "21:00",
            "gl": 0.31,
            "uscm": 568.5
        },
        {
            "date": "Thu 05-01-2023",
            "time": "22:00",
            "gl": 0.28,
            "uscm": 508.85
        },
        {
            "date": "Thu 05-01-2023",
            "time": "23:00",
            "gl": 0.28,
            "uscm": 512.08
        },
        {
            "date": "Fri 06-01-2023",
            "time": "00:00",
            "gl": 0.28,
            "uscm": 500.2
        },
        {
            "date": "Fri 06-01-2023",
            "time": "01:00",
            "gl": 0.24,
            "uscm": 443.23
        },
        {
            "date": "Fri 06-01-2023",
            "time": "02:00",
            "gl": 0.23,
            "uscm": 415.96
        },
        {
            "date": "Fri 06-01-2023",
            "time": "03:00",
            "gl": 0.21,
            "uscm": 387.01
        },
        {
            "date": "Fri 06-01-2023",
            "time": "04:00",
            "gl": 0.2,
            "uscm": 372.11
        },
        {
            "date": "Fri 06-01-2023",
            "time": "05:00",
            "gl": 0.2,
            "uscm": 358.64
        }
    ]
}