{
    "date": "20230128",
    "time": 1900,
    "output": [
        {
            "date": "Sat 28-01-2023",
            "time": "20:00",
            "gl": 3.38,
            "uscm": 6148.49
        },
        {
            "date": "Sat 28-01-2023",
            "time": "21:00",
            "gl": 3.54,
            "uscm": 6427.91
        },
        {
            "date": "Sat 28-01-2023",
            "time": "22:00",
            "gl": 3.62,
            "uscm": 6586.95
        },
        {
            "date": "Sat 28-01-2023",
            "time": "23:00",
            "gl": 3.91,
            "uscm": 7104.85
        },
        {
            "date": "Sun 29-01-2023",
            "time": "00:00",
            "gl": 4.36,
            "uscm": 7923.97
        },
        {
            "date": "Sun 29-01-2023",
            "time": "01:00",
            "gl": 4.68,
            "uscm": 8509.37
        },
        {
            "date": "Sun 29-01-2023",
            "time": "02:00",
            "gl": 4.73,
            "uscm": 8592.76
        },
        {
            "date": "Sun 29-01-2023",
            "time": "03:00",
            "gl": 4.69,
            "uscm": 8522.62
        },
        {
            "date": "Sun 29-01-2023",
            "time": "04:00",
            "gl": 4.34,
            "uscm": 7888.76
        },
        {
            "date": "Sun 29-01-2023",
            "time": "05:00",
            "gl": 4.04,
            "uscm": 7345.27
        },
        {
            "date": "Sun 29-01-2023",
            "time": "06:00",
            "gl": 3.73,
            "uscm": 6785.65
        },
        {
            "date": "Sun 29-01-2023",
            "time": "07:00",
            "gl": 3.31,
            "uscm": 6010.82
        },
        {
            "date": "Sun 29-01-2023",
            "time": "08:00",
            "gl": 3.24,
            "uscm": 5893.56
        },
        {
            "date": "Sun 29-01-2023",
            "time": "09:00",
            "gl": 3.32,
            "uscm": 6027.56
        },
        {
            "date": "Sun 29-01-2023",
            "time": "10:00",
            "gl": 3.43,
            "uscm": 6243.63
        },
        {
            "date": "Sun 29-01-2023",
            "time": "11:00",
            "gl": 3.9,
            "uscm": 7085.0
        },
        {
            "date": "Sun 29-01-2023",
            "time": "12:00",
            "gl": 4.38,
            "uscm": 7958.73
        },
        {
            "date": "Sun 29-01-2023",
            "time": "13:00",
            "gl": 4.78,
            "uscm": 8696.98
        },
        {
            "date": "Sun 29-01-2023",
            "time": "14:00",
            "gl": 4.96,
            "uscm": 9019.7
        },
        {
            "date": "Sun 29-01-2023",
            "time": "15:00",
            "gl": 4.92,
            "uscm": 8949.33
        },
        {
            "date": "Sun 29-01-2023",
            "time": "16:00",
            "gl": 4.79,
            "uscm": 8716.92
        },
        {
            "date": "Sun 29-01-2023",
            "time": "17:00",
            "gl": 4.38,
            "uscm": 7958.17
        },
        {
            "date": "Sun 29-01-2023",
            "time": "18:00",
            "gl": 3.87,
            "uscm": 7033.73
        },
        {
            "date": "Sun 29-01-2023",
            "time": "19:00",
            "gl": 3.42,
            "uscm": 6213.25
        }
    ]
}