{
    "date": "20230403",
    "time": 600,
    "output": [
        {
            "date": "Tue 04-04-2023",
            "time": "06:00",
            "gl": 3.38,
            "uscm": 6150.31
        },
        {
            "date": "Wed 05-04-2023",
            "time": "06:00",
            "gl": 3.24,
            "uscm": 5899.45
        },
        {
            "date": "Thu 06-04-2023",
            "time": "06:00",
            "gl": 3.41,
            "uscm": 6200.32
        },
        {
            "date": "Fri 07-04-2023",
            "time": "06:00",
            "gl": 3.48,
            "uscm": 6332.32
        },
        {
            "date": "Sat 08-04-2023",
            "time": "06:00",
            "gl": 3.1,
            "uscm": 5635.83
        },
        {
            "date": "Sun 09-04-2023",
            "time": "06:00",
            "gl": 3.25,
            "uscm": 5915.24
        },
        {
            "date": "Mon 10-04-2023",
            "time": "06:00",
            "gl": 2.98,
            "uscm": 5426.75
        },
        {
            "date": "Tue 11-04-2023",
            "time": "06:00",
            "gl": 3.11,
            "uscm": 5647.67
        },
        {
            "date": "Wed 12-04-2023",
            "time": "06:00",
            "gl": 3.19,
            "uscm": 5797.36
        },
        {
            "date": "Thu 13-04-2023",
            "time": "06:00",
            "gl": 3.16,
            "uscm": 5745.67
        },
        {
            "date": "Fri 14-04-2023",
            "time": "06:00",
            "gl": 2.74,
            "uscm": 4973.9
        },
        {
            "date": "Sat 15-04-2023",
            "time": "06:00",
            "gl": 2.61,
            "uscm": 4742.27
        },
        {
            "date": "Sun 16-04-2023",
            "time": "06:00",
            "gl": 2.67,
            "uscm": 4848.02
        },
        {
            "date": "Mon 17-04-2023",
            "time": "06:00",
            "gl": 2.4,
            "uscm": 4364.68
        }
    ]
}