{
    "date": "20230303",
    "time": 1000,
    "output": [
        {
            "date": "Fri 03-03-2023",
            "time": "11:00",
            "gl": 3.24,
            "uscm": 5889.92
        },
        {
            "date": "Fri 03-03-2023",
            "time": "12:00",
            "gl": 3.16,
            "uscm": 5740.39
        },
        {
            "date": "Fri 03-03-2023",
            "time": "13:00",
            "gl": 3.07,
            "uscm": 5575.91
        },
        {
            "date": "Fri 03-03-2023",
            "time": "14:00",
            "gl": 3.03,
            "uscm": 5506.33
        },
        {
            "date": "Fri 03-03-2023",
            "time": "15:00",
            "gl": 3.11,
            "uscm": 5658.86
        },
        {
            "date": "Fri 03-03-2023",
            "time": "16:00",
            "gl": 3.13,
            "uscm": 5697.41
        },
        {
            "date": "Fri 03-03-2023",
            "time": "17:00",
            "gl": 3.22,
            "uscm": 5850.54
        },
        {
            "date": "Fri 03-03-2023",
            "time": "18:00",
            "gl": 3.25,
            "uscm": 5914.4
        },
        {
            "date": "Fri 03-03-2023",
            "time": "19:00",
            "gl": 3.16,
            "uscm": 5745.48
        },
        {
            "date": "Fri 03-03-2023",
            "time": "20:00",
            "gl": 3.02,
            "uscm": 5496.02
        },
        {
            "date": "Fri 03-03-2023",
            "time": "21:00",
            "gl": 2.75,
            "uscm": 4993.83
        },
        {
            "date": "Fri 03-03-2023",
            "time": "22:00",
            "gl": 2.48,
            "uscm": 4509.12
        },
        {
            "date": "Fri 03-03-2023",
            "time": "23:00",
            "gl": 2.32,
            "uscm": 4225.51
        },
        {
            "date": "Sat 04-03-2023",
            "time": "00:00",
            "gl": 2.09,
            "uscm": 3795.92
        },
        {
            "date": "Sat 04-03-2023",
            "time": "01:00",
            "gl": 1.93,
            "uscm": 3502.6
        },
        {
            "date": "Sat 04-03-2023",
            "time": "02:00",
            "gl": 1.88,
            "uscm": 3413.68
        },
        {
            "date": "Sat 04-03-2023",
            "time": "03:00",
            "gl": 1.92,
            "uscm": 3488.43
        },
        {
            "date": "Sat 04-03-2023",
            "time": "04:00",
            "gl": 2.05,
            "uscm": 3733.44
        },
        {
            "date": "Sat 04-03-2023",
            "time": "05:00",
            "gl": 2.27,
            "uscm": 4124.55
        },
        {
            "date": "Sat 04-03-2023",
            "time": "06:00",
            "gl": 2.54,
            "uscm": 4623.93
        },
        {
            "date": "Sat 04-03-2023",
            "time": "07:00",
            "gl": 2.87,
            "uscm": 5222.03
        },
        {
            "date": "Sat 04-03-2023",
            "time": "08:00",
            "gl": 3.17,
            "uscm": 5758.97
        },
        {
            "date": "Sat 04-03-2023",
            "time": "09:00",
            "gl": 3.36,
            "uscm": 6117.76
        },
        {
            "date": "Sat 04-03-2023",
            "time": "10:00",
            "gl": 3.48,
            "uscm": 6334.6
        }
    ]
}