{
    "date": "20230308",
    "time": 800,
    "output": [
        {
            "date": "Wed 08-03-2023",
            "time": "09:00",
            "gl": 0.75,
            "uscm": 1364.25
        },
        {
            "date": "Wed 08-03-2023",
            "time": "10:00",
            "gl": 0.9,
            "uscm": 1637.6
        },
        {
            "date": "Wed 08-03-2023",
            "time": "11:00",
            "gl": 1.16,
            "uscm": 2103.86
        },
        {
            "date": "Wed 08-03-2023",
            "time": "12:00",
            "gl": 1.47,
            "uscm": 2667.83
        },
        {
            "date": "Wed 08-03-2023",
            "time": "13:00",
            "gl": 1.77,
            "uscm": 3221.02
        },
        {
            "date": "Wed 08-03-2023",
            "time": "14:00",
            "gl": 2.02,
            "uscm": 3665.7
        },
        {
            "date": "Wed 08-03-2023",
            "time": "15:00",
            "gl": 2.08,
            "uscm": 3790.53
        },
        {
            "date": "Wed 08-03-2023",
            "time": "16:00",
            "gl": 2.1,
            "uscm": 3824.84
        },
        {
            "date": "Wed 08-03-2023",
            "time": "17:00",
            "gl": 2.09,
            "uscm": 3807.81
        },
        {
            "date": "Wed 08-03-2023",
            "time": "18:00",
            "gl": 2.08,
            "uscm": 3773.24
        },
        {
            "date": "Wed 08-03-2023",
            "time": "19:00",
            "gl": 2.1,
            "uscm": 3810.71
        },
        {
            "date": "Wed 08-03-2023",
            "time": "20:00",
            "gl": 2.18,
            "uscm": 3969.86
        },
        {
            "date": "Wed 08-03-2023",
            "time": "21:00",
            "gl": 2.25,
            "uscm": 4098.24
        },
        {
            "date": "Wed 08-03-2023",
            "time": "22:00",
            "gl": 2.24,
            "uscm": 4080.68
        },
        {
            "date": "Wed 08-03-2023",
            "time": "23:00",
            "gl": 2.19,
            "uscm": 3990.3
        },
        {
            "date": "Thu 09-03-2023",
            "time": "00:00",
            "gl": 2.09,
            "uscm": 3805.41
        },
        {
            "date": "Thu 09-03-2023",
            "time": "01:00",
            "gl": 1.95,
            "uscm": 3541.89
        },
        {
            "date": "Thu 09-03-2023",
            "time": "02:00",
            "gl": 1.79,
            "uscm": 3252.03
        },
        {
            "date": "Thu 09-03-2023",
            "time": "03:00",
            "gl": 1.54,
            "uscm": 2806.13
        },
        {
            "date": "Thu 09-03-2023",
            "time": "04:00",
            "gl": 1.3,
            "uscm": 2358.34
        },
        {
            "date": "Thu 09-03-2023",
            "time": "05:00",
            "gl": 1.16,
            "uscm": 2114.2
        },
        {
            "date": "Thu 09-03-2023",
            "time": "06:00",
            "gl": 1.04,
            "uscm": 1882.6
        },
        {
            "date": "Thu 09-03-2023",
            "time": "07:00",
            "gl": 0.87,
            "uscm": 1575.71
        },
        {
            "date": "Thu 09-03-2023",
            "time": "08:00",
            "gl": 0.83,
            "uscm": 1515.92
        }
    ]
}